codabl/__init__.py
codabl/api_client.py
codabl/configuration.py
codabl/rest.py
codabl/api/__init__.py
codabl/api/anomaly_api.py
codabl/api/integrations_api.py
codabl/api/language_api.py
codabl/models/__init__.py
codabl/models/candle_request.py
codabl/models/candle_response.py
codabl/models/error.py
codabl/models/exchange.py
codabl/models/exchange_assets_response.py
codabl/models/exchange_assets_response_inner.py
codabl/models/ohclv.py
codabl/models/orderbook_request.py
codabl/models/orderbook_response.py
codabl/models/point_time_series.py
codabl/models/supported_exchanges.py
codabl/models/text.py
codabl/models/ticker_response.py
codabl/models/ticker_response_inner.py
codabl/models/time_series.py
test/__init__.py
test/test_anomaly_api.py
test/test_candle_request.py
test/test_candle_response.py
test/test_error.py
test/test_exchange.py
test/test_exchange_assets_response.py
test/test_exchange_assets_response_inner.py
test/test_integrations_api.py
test/test_language_api.py
test/test_ohclv.py
test/test_orderbook_request.py
test/test_orderbook_response.py
test/test_point_time_series.py
test/test_supported_exchanges.py
test/test_text.py
test/test_ticker_response.py
test/test_ticker_response_inner.py
test/test_time_series.py
codabl_python-0.1.2.dist-info/METADATA
codabl_python-0.1.2.dist-info/WHEEL
codabl_python-0.1.2.dist-info/top_level.txt
codabl_python-0.1.2.dist-info/RECORD
