Metadata-Version: 2.1
Name: codabl-python
Version: 0.1.2
Summary: Codabl Community API
Home-page: https://github.com/codabl/codabl-python
Author: UNKNOWN
Author-email: UNKNOWN
License: UNKNOWN
Keywords: Swagger,Codabl Community API
Platform: UNKNOWN
Requires-Dist: certifi (>=2017.4.17)
Requires-Dist: python-dateutil (>=2.1)
Requires-Dist: six (>=1.10)
Requires-Dist: urllib3 (>=1.23)
